switchinglogfilehandlers/__init__.py
switchinglogfilehandlers-0.0.5.dist-info/METADATA
switchinglogfilehandlers-0.0.5.dist-info/WHEEL
switchinglogfilehandlers-0.0.5.dist-info/licenses/LICENSE
switchinglogfilehandlers-0.0.5.dist-info/RECORD
