Metadata-Version: 2.3
Name: switchinglogfilehandlers
Version: 0.0.5
Summary: A collection of switching log file handlers
Project-URL: Homepage, https://git.hjp.at:3000/hjp/switchinglogfilehandlers
Project-URL: Bug Tracker, https://git.hjp.at:3000/hjp/switchinglogfilehandlers/issues
Author-email: "Peter J. Holzer" <hjp@hjp.at>
License-File: LICENSE
Classifier: License :: OSI Approved :: MIT License
Classifier: Operating System :: OS Independent
Classifier: Programming Language :: Python :: 3
Requires-Python: >=3.7
